sitemap_maker/__init__.py
sitemap_maker/__main__.py
sitemap_maker/sitemap.py
sitemap_maker-1.0.1.dist-info/LICENSE
sitemap_maker-1.0.1.dist-info/METADATA
sitemap_maker-1.0.1.dist-info/WHEEL
sitemap_maker-1.0.1.dist-info/entry_points.txt
sitemap_maker-1.0.1.dist-info/top_level.txt
sitemap_maker-1.0.1.dist-info/RECORD
